bcrpy/__init__.py
bcrpy/_fetcher.py
bcrpy/_metadata.py
bcrpy/_old/utils.py
bcrpy/hacha.py
bcrpy/main.py
bcrpy/utils.py
bcrpy-3.3.1.dist-info/LICENSE
bcrpy-3.3.1.dist-info/METADATA
bcrpy-3.3.1.dist-info/WHEEL
bcrpy-3.3.1.dist-info/RECORD
