Metadata-Version: 2.3
Name: bcrpy
Version: 3.3.1
Summary: An API client for the extraction, query, and analysis of the BCRPData database from the Central Reserve Bank of Peru (BCRP).
License: MIT
Author: andrewrgarcia
Author-email: garcia.gtr@gmail.com
Requires-Python: >=3.8,<3.13
Classifier: License :: OSI Approved :: MIT License
Classifier: Programming Language :: Python :: 3
Classifier: Programming Language :: Python :: 3.8
Classifier: Programming Language :: Python :: 3.9
Classifier: Programming Language :: Python :: 3.10
Classifier: Programming Language :: Python :: 3.11
Classifier: Programming Language :: Python :: 3.12
Requires-Dist: bottleneck (>=1.3.6,<2.0.0)
Requires-Dist: colorama (>=0.4.6,<0.5.0)
Requires-Dist: numpy (>=1.24,<1.25) ; python_version < "3.9"
Requires-Dist: numpy (>=1.26,<2.0) ; python_version >= "3.9"
Requires-Dist: pandas (>=1.5,<2.1) ; python_version < "3.11"
Requires-Dist: pandas (>=2.2,<2.3) ; python_version >= "3.11"
Requires-Dist: pathos (>=0.3.1,<0.4.0)
Requires-Dist: requests (>=2.28.2,<3.0.0)
Requires-Dist: tabulate (>=0.9.0,<0.10.0)
Requires-Dist: termcolor (>=2.4.0,<3.0.0)
Requires-Dist: tqdm (>=4.65.0,<5.0.0)
Project-URL: Changelog, https://github.com/andrewrgarcia/bcrpy/releases
Project-URL: Documentation, https://bcrpy.readthedocs.io
Project-URL: Homepage, https://bcrpy.vercel.app/
Project-URL: Issues, https://github.com/andrewrgarcia/bcrpy/issues
Project-URL: Repository, https://github.com/andrewrgarcia/bcrpy
